mhkit/__init__.py
mhkit/warnings.py
mhkit/acoustics/__init__.py
mhkit/acoustics/analysis.py
mhkit/acoustics/graphics.py
mhkit/acoustics/io.py
mhkit/acoustics/sel.py
mhkit/acoustics/spl.py
mhkit/dolfyn/__init__.py
mhkit/dolfyn/binned.py
mhkit/dolfyn/time.py
mhkit/dolfyn/velocity.py
mhkit/dolfyn/adp/__init__.py
mhkit/dolfyn/adp/api.py
mhkit/dolfyn/adp/clean.py
mhkit/dolfyn/adp/discharge.py
mhkit/dolfyn/adp/turbulence.py
mhkit/dolfyn/adv/__init__.py
mhkit/dolfyn/adv/api.py
mhkit/dolfyn/adv/clean.py
mhkit/dolfyn/adv/motion.py
mhkit/dolfyn/adv/turbulence.py
mhkit/dolfyn/io/__init__.py
mhkit/dolfyn/io/api.py
mhkit/dolfyn/io/base.py
mhkit/dolfyn/io/nortek.py
mhkit/dolfyn/io/nortek2.py
mhkit/dolfyn/io/nortek2_defs.py
mhkit/dolfyn/io/nortek2_lib.py
mhkit/dolfyn/io/nortek_defs.py
mhkit/dolfyn/io/nortek_lib.py
mhkit/dolfyn/io/rdi.py
mhkit/dolfyn/io/rdi_defs.py
mhkit/dolfyn/io/rdi_lib.py
mhkit/dolfyn/rotate/__init__.py
mhkit/dolfyn/rotate/api.py
mhkit/dolfyn/rotate/awac.py
mhkit/dolfyn/rotate/base.py
mhkit/dolfyn/rotate/rdi.py
mhkit/dolfyn/rotate/signature.py
mhkit/dolfyn/rotate/vector.py
mhkit/dolfyn/tools/__init__.py
mhkit/dolfyn/tools/fft.py
mhkit/dolfyn/tools/misc.py
mhkit/loads/__init__.py
mhkit/loads/general.py
mhkit/loads/graphics.py
mhkit/loads/extreme/__init__.py
mhkit/loads/extreme/extremes.py
mhkit/loads/extreme/mler.py
mhkit/loads/extreme/peaks.py
mhkit/loads/extreme/sample.py
mhkit/mooring/__init__.py
mhkit/mooring/graphics.py
mhkit/mooring/io.py
mhkit/mooring/main.py
mhkit/power/__init__.py
mhkit/power/characteristics.py
mhkit/power/quality.py
mhkit/qc/__init__.py
mhkit/river/__init__.py
mhkit/river/graphics.py
mhkit/river/performance.py
mhkit/river/resource.py
mhkit/river/io/__init__.py
mhkit/river/io/d3d.py
mhkit/river/io/usgs.py
mhkit/tests/__init__.py
mhkit/tests/acoustics/__init__.py
mhkit/tests/acoustics/test_analysis.py
mhkit/tests/acoustics/test_io.py
mhkit/tests/acoustics/test_metrics.py
mhkit/tests/dolfyn/__init__.py
mhkit/tests/dolfyn/base.py
mhkit-1.0.1.dist-info/licenses/LICENSE.md
mhkit-1.0.1.dist-info/METADATA
mhkit-1.0.1.dist-info/WHEEL
mhkit-1.0.1.dist-info/top_level.txt
mhkit-1.0.1.dist-info/RECORD
