Metadata-Version: 2.4
Name: mhkit
Version: 1.0.1
Summary: Marine and Hydrokinetic Toolkit
Author: MHKiT developers
License: Revised BSD
Project-URL: Homepage, https://github.com/MHKiT-Software/mhkit-python
Project-URL: Documentation, https://mhkit-software.github.io/MHKiT
Classifier: Development Status :: 3 - Alpha
Classifier: Programming Language :: Python :: 3
Classifier: Topic :: Scientific/Engineering
Classifier: Intended Audience :: Science/Research
Classifier: Operating System :: OS Independent
Requires-Python: >=3.10
License-File: LICENSE.md
Requires-Dist: numpy>=2.0.0
Requires-Dist: pandas>=2.2.2
Requires-Dist: scipy>=1.14.0
Requires-Dist: xarray>=2024.6.0
Requires-Dist: matplotlib>=3.9.1
Requires-Dist: pecos>=0.3.0
Requires-Dist: requests
Provides-Extra: wave
Requires-Dist: scikit-learn>=1.5.1; extra == "wave"
Requires-Dist: statsmodels>=0.14.2; extra == "wave"
Requires-Dist: netCDF4>=1.7.1.post1; extra == "wave"
Requires-Dist: pytz; extra == "wave"
Requires-Dist: NREL-rex>=0.2.63; extra == "wave"
Requires-Dist: beautifulsoup4; extra == "wave"
Requires-Dist: bottleneck; extra == "wave"
Requires-Dist: lxml; extra == "wave"
Provides-Extra: tidal
Requires-Dist: netCDF4>=1.7.1.post1; extra == "tidal"
Requires-Dist: bottleneck; extra == "tidal"
Provides-Extra: river
Requires-Dist: netCDF4>=1.7.1.post1; extra == "river"
Requires-Dist: bottleneck; extra == "river"
Provides-Extra: dolfyn
Requires-Dist: h5py>=3.11.0; extra == "dolfyn"
Requires-Dist: h5pyd>=0.18.0; extra == "dolfyn"
Requires-Dist: netCDF4>=1.7.1.post1; extra == "dolfyn"
Requires-Dist: cartopy; extra == "dolfyn"
Provides-Extra: power
Provides-Extra: loads
Requires-Dist: fatpack; extra == "loads"
Requires-Dist: statsmodels>=0.14.2; extra == "loads"
Requires-Dist: scikit-learn>=1.5.1; extra == "loads"
Provides-Extra: mooring
Provides-Extra: acoustics
Provides-Extra: qc
Provides-Extra: utils
Provides-Extra: dev
Requires-Dist: pytest; extra == "dev"
Requires-Dist: pylint; extra == "dev"
Requires-Dist: pytest-cov; extra == "dev"
Requires-Dist: pre-commit; extra == "dev"
Requires-Dist: coverage; extra == "dev"
Requires-Dist: coveralls; extra == "dev"
Provides-Extra: all
Requires-Dist: mhkit[wave]; extra == "all"
Requires-Dist: mhkit[tidal]; extra == "all"
Requires-Dist: mhkit[river]; extra == "all"
Requires-Dist: mhkit[dolfyn]; extra == "all"
Requires-Dist: mhkit[power]; extra == "all"
Requires-Dist: mhkit[loads]; extra == "all"
Requires-Dist: mhkit[mooring]; extra == "all"
Requires-Dist: mhkit[acoustics]; extra == "all"
Requires-Dist: mhkit[qc]; extra == "all"
Requires-Dist: mhkit[utils]; extra == "all"
Provides-Extra: examples
Requires-Dist: jupyter; extra == "examples"
Requires-Dist: notebook; extra == "examples"
Requires-Dist: ipykernel; extra == "examples"
Requires-Dist: nbval; extra == "examples"
Requires-Dist: utm; extra == "examples"
Requires-Dist: folium; extra == "examples"
Requires-Dist: mhkit[all]; extra == "examples"
Dynamic: license-file
